QQMusicAPI/__init__.py
QQMusicAPI/pager.py
QQMusicAPI/qqmusic.py
QQMusicAPI/singer.py
QQMusicAPI/song.py
qqmusic_api-0.1.dist-info/METADATA
qqmusic_api-0.1.dist-info/WHEEL
qqmusic_api-0.1.dist-info/top_level.txt
qqmusic_api-0.1.dist-info/RECORD
