Metadata-Version: 2.1
Name: qqmusic-api
Version: 0.1
Summary: some api about qqmusic
Home-page: https://github.com/MeiK-h/QQMusicAPI
Author: MeiK-H
Author-email: meik2333@gmail.com
License: MIT
Platform: UNKNOWN
Classifier: License :: OSI Approved :: MIT License
Classifier: Programming Language :: Python
Classifier: Programming Language :: Python :: 3
Classifier: Programming Language :: Python :: 3.6
Classifier: Programming Language :: Python :: Implementation :: CPython
Classifier: Programming Language :: Python :: Implementation :: PyPy
Requires-Python: >=3.5.0
